[
  {
    "key": "oxygen_len_p5",
    "min": 373.0,
    "max": 530.0,
    "step": 1.0,
    "mean": 449.6295882936508,
    "median": 449.0
  },
  {
    "key": "oxygen_bu_p5",
    "min": 264.43,
    "max": 496.77,
    "step": 0.009999999999990905,
    "mean": 374.2347188081937,
    "median": 369.55
  },
  {
    "key": "small_lump",
    "min": 0.0,
    "max": 1025.0,
    "step": 1.0,
    "mean": 444.0909518213866,
    "median": 406.0
  },
  {
    "key": "oxygen_len_p8",
    "min": 169.0,
    "max": 299.0,
    "step": 1.0,
    "mean": 225.12227452923688,
    "median": 222.0
  },
  {
    "key": "coal_stain_p8",
    "min": 132.0,
    "max": 546.0,
    "step": 1.0,
    "mean": 320.02753659141655,
    "median": 316.0
  },
  {
    "key": "coal_gsk_p8",
    "min": 62.0,
    "max": 421.0,
    "step": 1.0,
    "mean": 209.37132580925214,
    "median": 199.0
  },
  {
    "key": "precipitator_gun_p8",
    "min": 1712.0,
    "max": 2100.95,
    "step": 0.009999999999763531,
    "mean": 1938.908485224733,
    "median": 1952.18
  },
  {
    "key": "coal_stain_p5",
    "min": 0.0,
    "max": 325.0,
    "step": 1.0,
    "mean": 135.42831941667646,
    "median": 136.0
  },
  {
    "key": "Briquette_HP1",
    "min": 0.0,
    "max": 522.0,
    "step": 1.0,
    "mean": 176.0806130806131,
    "median": 105.0
  },
  {
    "key": "coal_gsk_p5",
    "min": 22.0,
    "max": 355.0,
    "step": 1.0,
    "mean": 150.24931778714958,
    "median": 134.0
  }
]